talk_in_code/__init__.py
talk_in_code/pt_translator.py
talk_in_code/translate.py
talk_in_code-0.0.4.dist-info/LICENSE
talk_in_code-0.0.4.dist-info/METADATA
talk_in_code-0.0.4.dist-info/WHEEL
talk_in_code-0.0.4.dist-info/dependency_links.txt
talk_in_code-0.0.4.dist-info/top_level.txt
talk_in_code-0.0.4.dist-info/RECORD
