Metadata-Version: 2.1
Name: talk-in-code
Version: 0.0.4
Summary: Transform natural language strings on Python runnable code
Home-page: UNKNOWN
Author: Itanú Romero
License: UNKNOWN
Platform: UNKNOWN
Classifier: Programming Language :: Python :: 3
Classifier: License :: OSI Approved :: MIT License
Classifier: Operating System :: OS Independent
Requires-Python: >=3.8
License-File: LICENSE
